hovercraft/__init__.py
hovercraft/converter.py
hovercraft/generate.py
hovercraft/parse.py
hovercraft/position.py
hovercraft/template.py
hovercraft/templates/reST.xsl
hovercraft/templates/default/template.cfg
hovercraft/templates/default/template.xsl
hovercraft/templates/default/css/highlight.css
hovercraft/templates/default/css/hovercraft.css
hovercraft/templates/default/js/gotoSlide.js
hovercraft/templates/default/js/hovercraft.js
hovercraft/templates/default/js/impress.js
hovercraft/templates/default/js/MathJax/es5/core.js
hovercraft/templates/default/js/MathJax/es5/latest.js
hovercraft/templates/default/js/MathJax/es5/loader.js
hovercraft/templates/default/js/MathJax/es5/mml-chtml.js
hovercraft/templates/default/js/MathJax/es5/mml-svg.js
hovercraft/templates/default/js/MathJax/es5/node-main.js
hovercraft/templates/default/js/MathJax/es5/startup.js
hovercraft/templates/default/js/MathJax/es5/tex-chtml-full-speech.js
hovercraft/templates/default/js/MathJax/es5/tex-chtml-full.js
hovercraft/templates/default/js/MathJax/es5/tex-chtml.js
hovercraft/templates/default/js/MathJax/es5/tex-mml-chtml.js
hovercraft/templates/default/js/MathJax/es5/tex-mml-svg.js
hovercraft/templates/default/js/MathJax/es5/tex-svg-full.js
hovercraft/templates/default/js/MathJax/es5/tex-svg.js
hovercraft/templates/default/js/MathJax/es5/a11y/assistive-mml.js
hovercraft/templates/default/js/MathJax/es5/a11y/complexity.js
hovercraft/templates/default/js/MathJax/es5/a11y/explorer.js
hovercraft/templates/default/js/MathJax/es5/a11y/semantic-enrich.js
hovercraft/templates/default/js/MathJax/es5/a11y/sre.js
hovercraft/templates/default/js/MathJax/es5/adaptors/liteDOM.js
hovercraft/templates/default/js/MathJax/es5/input/asciimath.js
hovercraft/templates/default/js/MathJax/es5/input/mml.js
hovercraft/templates/default/js/MathJax/es5/input/tex-base.js
hovercraft/templates/default/js/MathJax/es5/input/tex-full.js
hovercraft/templates/default/js/MathJax/es5/input/tex.js
prezentprogramo-3.2.dist-info/licenses/LICENSE.txt
prezentprogramo-3.2.dist-info/METADATA
prezentprogramo-3.2.dist-info/WHEEL
prezentprogramo-3.2.dist-info/entry_points.txt
prezentprogramo-3.2.dist-info/top_level.txt
prezentprogramo-3.2.dist-info/RECORD
