Metadata-Version: 2.4
Name: Prezentprogramo
Version: 3.2
Summary: Makes impress.js presentations from reStructuredText
Author-email: Ahmad Yoosofan <yoosofan@gmx.com>
License-Expression: GPL-3.0-or-later
Project-URL: Homepage, https://github.com/yoosofan/prezentprogramo
Project-URL: Issues, https://github.com/yoosofan/prezentprogramo/issues
Keywords: presentations,restructuredtext
Classifier: Programming Language :: Python :: 3
Classifier: Operating System :: OS Independent
Classifier: Development Status :: 5 - Production/Stable
Classifier: Topic :: Multimedia :: Graphics :: Presentation
Classifier: Topic :: Text Processing
Classifier: Programming Language :: Python :: 3 :: Only
Classifier: Programming Language :: Python :: 3.10
Classifier: Programming Language :: Python :: 3.11
Classifier: Programming Language :: Python :: 3.12
Classifier: Programming Language :: Python :: 3.13
Requires-Python: >=3.10
License-File: LICENSE.txt
Requires-Dist: wheel
Requires-Dist: docutils>=0.21
Requires-Dist: lxml>=3.1.0
Requires-Dist: svg.path
Requires-Dist: pygments
Requires-Dist: watchdog
Requires-Dist: ghostscript
Requires-Dist: packaging
Requires-Dist: selenium
Requires-Dist: webdriver_manager
Requires-Dist: screeninfo
Requires-Dist: graphviz
Requires-Dist: beautifulsoup4
Provides-Extra: test
Requires-Dist: pytest; extra == "test"
Requires-Dist: pytest-cov; extra == "test"
Requires-Dist: manuel; extra == "test"
Provides-Extra: testing
Requires-Dist: manuel; extra == "testing"
Dynamic: license-file
